yuzu/__init__.py
yuzu/cache.py
yuzu/logging.py
yuzu/py.typed
yuzu-4.1.1.dist-info/LICENSE
yuzu-4.1.1.dist-info/WHEEL
yuzu-4.1.1.dist-info/METADATA
yuzu-4.1.1.dist-info/RECORD
