Metadata-Version: 2.1
Name: yuzu
Version: 4.1.1
Summary: Lightweight and useful annotation package for logging and caching
Home-page: https://github.com/hotoku/yuzu
License: MIT
Author: Yasunori Horikoshi
Author-email: hotoku@users.noreply.github.com
Requires-Python: >=3.7,<4.0
Classifier: License :: OSI Approved :: MIT License
Classifier: Programming Language :: Python :: 3
Classifier: Programming Language :: Python :: 3.7
Classifier: Programming Language :: Python :: 3.8
Classifier: Programming Language :: Python :: 3.9
Project-URL: Repository, https://github.com/hotoku/yuzu
